PIPWeb/__init__.py
PIPWeb/app.py
PIPWeb-2021.3.3.dist-info/METADATA
PIPWeb-2021.3.3.dist-info/WHEEL
PIPWeb-2021.3.3.dist-info/entry_points.txt
PIPWeb-2021.3.3.dist-info/top_level.txt
PIPWeb-2021.3.3.dist-info/RECORD
